odin_messages/__init__.py
odin_messages/accounting.py
odin_messages/balance.py
odin_messages/base.py
odin_messages/manager.py
odin_messages/monitor.py
odin_messages/order_array.py
odin_messages/orderbook.py
odin_messages/orders.py
odin_messages/prices.py
odin_messages/tradewatch.py
odin_messages-0.5.1.dist-info/WHEEL
odin_messages-0.5.1.dist-info/METADATA
odin_messages-0.5.1.dist-info/RECORD
