Metadata-Version: 2.1
Name: odin-messages
Version: 0.5.1
Summary: 
Author: adolfrodeno
Author-email: amvillalobos@uc.cl
Requires-Python: >=3.8,<4.0
Classifier: Programming Language :: Python :: 3
Classifier: Programming Language :: Python :: 3.10
Classifier: Programming Language :: Python :: 3.8
Classifier: Programming Language :: Python :: 3.9
Requires-Dist: autopep8 (>=1.6.0,<2.0.0)
Requires-Dist: pydantic (>=1.8.2,<2.0.0)
